rtl/register.sv
/*
 * Copyright 2023 BSC*
 * *Barcelona Supercomputing Center (BSC)
 * 
 * SPDX-License-Identifier: Apache-2.0 WITH SHL-2.1
 * 
 * Licensed under the Solderpad Hardware License v 2.1 (the “License”); you
 * may not use this file except in compliance with the License, or, at your
 * option, the Apache License version 2.0. You may obtain a copy of the
 * License at
 * 
 * https://solderpad.org/licenses/SHL-2.1/
 * 
 * Unless required by applicable law or agreed to in writing, any work
 * distributed under the License is distributed on an “AS IS” BASIS, WITHOUT
 * WARRANTIES OR CONDITIONS OF ANY KIND, either express or implied. See the
 * License for the specific language governing permissions and limitations
 * under the License.
 */

`default_nettype none

module register #(
    parameter WIDTH = 64
) (
    input wire clk_i,
    input wire rstn_i,
    input wire flush_i,
    input wire load_i,
    input wire [WIDTH-1:0] input_i,
    output reg [WIDTH-1:0] output_o
);
    
    always @(posedge clk_i, negedge rstn_i) begin
        if (~rstn_i) begin
            output_o <= 0;
        end else if (flush_i) begin
            output_o <= 0;
        end else if (load_i) begin
            output_o <= input_i;
        end else begin
            output_o <= output_o;
        end
    end

endmodule

`default_nettype wire

tb/tb_register/tb_module.sv
//-----------------------------
// Header
//-----------------------------

/* -----------------------------------------------
* Project Name   : DRAC
* File           : .v
* Organization   : Barcelona Supercomputing Center
* Author(s)      : 
* Email(s)       : @bsc.es
* References     : 
* -----------------------------------------------
* Revision History
*  Revision   | Author     | Commit | Description
* -----------------------------------------------
*/

//-----------------------------
// includes
//-----------------------------

`timescale 1 ns / 1 ns
`default_nettype none

`include "colors.vh"
import drac_pkg::*;

module tb_module();



//-----------------------------
// Local parameters
//-----------------------------
    parameter VERBOSE         = 1;
    parameter CLK_PERIOD      = 2;
    parameter CLK_HALF_PERIOD = CLK_PERIOD / 2;
//***DUT parameters***    
    //parameter TB_DATA_WIDTH = 32;
    //parameter TB_WEIGHTS_WIDTH = 7;
    //parameter TB_N_CORES = 1;
    //parameter TB_CORE_EVENTS = 1;

//-----------------------------
// Signals
//-----------------------------
reg tb_clk_i;
reg tb_rstn_i;
reg tb_flush_i;
reg tb_load_i;
bus32_t tb_inst;
bus32_t tb_inst_o;
//store name of test for easier debug of waveform
reg[64*8:0] tb_test_name;

//-----------------------------
// Module
//-----------------------------

register #(32) module_inst (
    .clk_i(tb_clk_i),
    .rstn_i(tb_rstn_i),
    .flush_i(tb_flush_i),
    .load_i(tb_load_i),
    .input_i(tb_inst),
    .output_o(tb_inst_o),
    .flush_i(tb_flush_i)
);

//-----------------------------
// DUT
//-----------------------------

//***clk_gen***
// A single clock source is used in this design.
    initial tb_clk_i = 1;
    always #CLK_HALF_PERIOD tb_clk_i = !tb_clk_i;

    //***task automatic reset_dut***
    task automatic reset_dut;
        begin
            $display("*** Toggle reset.");
            tb_rstn_i <= 1'b0;
            #CLK_PERIOD;
            tb_rstn_i <= 1'b1;
            #CLK_PERIOD;
            $display("Done");
        end
    endtask

//***task automatic init_sim***
    task automatic init_sim;
        begin
            $display("*** init_sim");
            tb_clk_i <='{default:1};
            tb_rstn_i<='{default:0};
	    tb_flush_i<='{default:0};
            tb_load_i<='{default:0};
            tb_inst<='{default:0};
            $display("Done");
        end
    endtask

//***task automatic init_dump***
//This task dumps the ALL signals of ALL levels of instance dut_example into the test.vcd file
//If you want a subset to modify the parameters of $dumpvars
    task automatic init_dump;
        begin
            $display("*** init_dump");
            $dumpfile("dum_file.vcd");
            $dumpvars(0,module_inst);
        end
    endtask

//***task automatic test_sim***
    task automatic test_sim;
        begin
            $display("*** test_sim");
            test_sim_1();
            reset_dut();
            test_sim_2();
            reset_dut();
            test_sim_3();
            reset_dut();
            test_sim_4();
            reset_dut();
        end
    endtask

// Test load register
    task automatic test_sim_1;
        begin
            int unsigned tmp = 0;
            tb_load_i <= 1;
            tb_test_name = "test_sim_1";
            $random(10);
            @(negedge tb_clk_i);
            for(int i = 0; i < 10; i++) begin
                tb_inst <= $urandom();
                //wait(tb_clk_i == 0);
                //wait(tb_clk_i == 1);
                //#CLK_PERIOD;
                @(posedge tb_clk_i);
                @(negedge tb_clk_i);
                if (tb_inst_o != tb_inst) begin
                    tmp = 1;
                    `START_RED_PRINT
                    $error("Result incorrect out: %d != correct: %d",tb_inst_o,tb_inst);
                    $error("clk %d",tb_clk_i);
                    `END_COLOR_PRINT
                end
            end
            if (tmp == 1) begin
                `START_RED_PRINT
                    $display("TEST LOAD FAILED.");
                `END_COLOR_PRINT
            end else begin
                `START_GREEN_PRINT
                    $display("TEST LOAD PASSED.");
                `END_COLOR_PRINT
            end
        end
    endtask

// Test no load register
    task automatic test_sim_2;
        begin
            int unsigned tmp = 0;
            int unsigned aux = 0;
            tb_test_name = "test_sim_2";
            $random(10);
            // Load first value
            tb_load_i <= 1;
            aux = $urandom();
            tb_inst <= aux;
            #CLK_PERIOD;
            // Turn off load
            tb_load_i <= 0;
            for(int i = 0; i < 10; i++) begin
                tb_inst <= $urandom();
                #CLK_PERIOD;
                if (tb_inst_o != aux) begin
                    tmp = 1;
                    `START_RED_PRINT
                    $error("Result incorrect out: %d != correct: %d",tb_inst_o,aux);
                    `END_COLOR_PRINT
                end
            end
            if (tmp == 1) begin
                `START_RED_PRINT
                        $display("TEST NO LOAD FAILED.");
                `END_COLOR_PRINT
            end else begin
                `START_GREEN_PRINT
                        $display("TEST NO LOAD PASSED.");
                `END_COLOR_PRINT
            end
        end
    endtask

// Test reset register
    task automatic test_sim_3;
        begin
            int unsigned tmp = 0;
            tb_test_name = "test_sim_3";
            $random(10);
            tb_load_i <= 1;
            tb_inst <= $urandom();
            #CLK_PERIOD;
            tb_rstn_i <= 0;
            for(int i = 0; i < 10; i++) begin
                tb_inst <= $urandom();
                #CLK_PERIOD;
                if (tb_inst_o != 0) begin
                    tmp = 1;
                    `START_RED_PRINT
                    $error("Result incorrect out: %d",tb_inst_o);
                    `END_COLOR_PRINT
                end
            end
            if (tmp == 1) begin
                `START_RED_PRINT
                        $display("TEST RESET FAILED.");
                `END_COLOR_PRINT
            end else begin
                `START_GREEN_PRINT
                        $display("TEST RESET PASSED.");
                `END_COLOR_PRINT
            end
        end
    endtask

    // Test flush register
    task automatic test_sim_4;
        begin
            int unsigned tmp = 0;
            tb_test_name = "test_sim_4";
            $random(10);
            tb_load_i <= 1;
            tb_inst <= $urandom();
            tb_flush_i <= 1;
            #CLK_PERIOD;
            for(int i = 0; i < 10; i++) begin
                tb_inst <= $urandom();
                #CLK_PERIOD;
                if (tb_inst_o != 0) begin
                    tmp = 1;
                    `START_RED_PRINT
                    $error("Result incorrect out: %d",tb_inst_o);
                    `END_COLOR_PRINT
                end
            end
            if (tmp == 1) begin
                `START_RED_PRINT
                        $display("TEST FLUSH FAILED.");
                `END_COLOR_PRINT
            end else begin
                `START_GREEN_PRINT
                        $display("TEST FLUSH PASSED.");
                `END_COLOR_PRINT
            end
        end
    endtask


//***init_sim***
//The tasks that compose my testbench are executed here, feel free to add more tasks.
    initial begin
        init_sim();
        init_dump();
        reset_dut();
        test_sim();
        $finish;
    end


endmodule
`default_nettype wire

tb/tb_register/dum_file.vcd
$date
	Tue Apr  7 16:27:54 2020
$end
$version
	ModelSim Version 10.5b
$end
$timescale
	1ns
$end

$scope module tb_module $end

$scope module module_inst $end
$var parameter 32 ! WIDTH $end
$var wire 1 " clk_i $end
$var wire 1 # rstn_i $end
$var wire 1 $ flush_i $end
$var wire 1 % load_i $end
$var wire 1 & input_i [31] $end
$var wire 1 ' input_i [30] $end
$var wire 1 ( input_i [29] $end
$var wire 1 ) input_i [28] $end
$var wire 1 * input_i [27] $end
$var wire 1 + input_i [26] $end
$var wire 1 , input_i [25] $end
$var wire 1 - input_i [24] $end
$var wire 1 . input_i [23] $end
$var wire 1 / input_i [22] $end
$var wire 1 0 input_i [21] $end
$var wire 1 1 input_i [20] $end
$var wire 1 2 input_i [19] $end
$var wire 1 3 input_i [18] $end
$var wire 1 4 input_i [17] $end
$var wire 1 5 input_i [16] $end
$var wire 1 6 input_i [15] $end
$var wire 1 7 input_i [14] $end
$var wire 1 8 input_i [13] $end
$var wire 1 9 input_i [12] $end
$var wire 1 : input_i [11] $end
$var wire 1 ; input_i [10] $end
$var wire 1 < input_i [9] $end
$var wire 1 = input_i [8] $end
$var wire 1 > input_i [7] $end
$var wire 1 ? input_i [6] $end
$var wire 1 @ input_i [5] $end
$var wire 1 A input_i [4] $end
$var wire 1 B input_i [3] $end
$var wire 1 C input_i [2] $end
$var wire 1 D input_i [1] $end
$var wire 1 E input_i [0] $end
$var reg 32 F output_o [31:0] $end
$upscope $end
$upscope $end
$enddefinitions $end
#0
$dumpvars
b0 F
b100000 !
1"
0#
0%
0E
0D
0C
0B
0A
0@
0?
0>
0=
0<
0;
0:
09
08
07
06
05
04
03
02
01
00
0/
0.
0-
0,
0+
0*
0)
0(
0'
0&
z$
$end
#1
0"
#2
1"
1#
#3
0"
#4
1"
1%
#5
0"
1D
1A
1@
1?
1=
1<
1;
15
13
12
11
10
1-
1+
1*
1&
#6
1"
b10001101001111010000011101110010 F
#7
0"
0?
1>
0=
0<
0;
18
16
05
14
01
00
1/
0-
1,
0*
1(
0&
#8
1"
b100110010011101010000010110010 F
#9
0"
0D
0@
0>
1<
1;
1:
17
06
15
04
02
1.
1-
0+
1&
#10
1"
b10100011110001010110111000010000 F
#11
0"
1@
1=
0<
0:
19
16
03
12
11
0/
0.
1+
1*
0(
0&
#12
1"
b1111000110011111010100110000 F
#13
0"
1E
1C
1>
1<
09
13
01
1/
0+
1&
#14
1"
b10001011010011011110011110110101 F
#15
0"
0E
1D
0<
1:
06
05
14
03
1.
0-
1+
1)
1'
0&
#16
1"
b1011110110010100110110110110110 F
#17
0"
0D
0@
0>
1<
0;
08
16
15
04
10
0/
0,
0+
0*
1(
0'
1&
#18
1"
b10110000101010011100101100010100 F
#19
0"
1E
1D
1B
1?
1>
0=
0<
1;
19
07
05
13
02
1/
1-
1,
1*
0(
1'
0&
#20
1"
b1011011111001001001110011011111 F
#21
0"
0C
1@
0?
1<
09
18
14
11
00
0.
0-
0,
1+
0*
0)
0'
1&
#22
1"
b10000100010101101010111010111011 F
#23
0"
0A
1?
1=
0;
19
06
15
03
01
10
1.
1-
1'
0&
#24
1"
b1000101111000110011101111101011 F
#25
0"
0#
b0 F
#26
1"
#27
0"
1#
#28
1"
b1000101111000110011101111101011 F
#29
0"
0D
0B
0@
0>
0=
0<
1;
0:
09
08
17
05
13
12
11
0.
0-
1,
0+
1(
1&
#30
1"
b11100010011111100100010001000001 F
#31
0"
0%
0E
0;
01
00
1-
1*
0'
0&
#32
1"
#33
0"
1D
1B
0?
1>
1=
19
18
16
03
02
11
1.
0,
1+
1)
0(
1&
#34
1"
#35
0"
1E
0B
0>
1<
09
04
13
01
0-
0+
0*
#36
1"
#37
0"
0E
0D
1C
1B
1A
1@
1?
1>
0<
1;
19
08
06
14
12
0.
1,
1+
0)
1(
#38
1"
#39
0"
1E
0@
0>
0=
07
16
15
11
10
1.
0,
#40
1"
#41
0"
0?
1<
0;
09
17
03
01
00
1,
0+
1*
0(
#42
1"
#43
0"
0E
1D
0C
0A
1@
1?
1:
18
07
06
04
02
10
0.
0*
1)
1(
1'
0&
#44
1"
#45
0"
1C
0B
1A
0@
0?
1=
0<
0:
19
16
14
11
0,
1*
0(
0'
#46
1"
#47
0"
1E
1B
1@
1;
06
13
0/
1-
1,
1+
0*
0)
#48
1"
#49
0"
0C
0B
0A
0=
1<
17
04
01
1.
0-
0+
1*
1(
1&
#50
1"
#51
0"
0#
b0 F
#52
1"
#53
0"
1#
#54
1"
#55
0"
1%
0E
0D
1B
1>
1=
0<
08
05
1/
1-
0*
1)
0(
1'
#56
1"
b11010011111001000101010110101000 F
#57
0"
0B
1A
0@
0=
1<
1:
09
18
07
16
03
1*
1(
0'
0#
b0 F
#58
1"
#59
0"
1E
1C
0A
1@
0>
0<
0:
08
17
14
00
0/
0.
0,
1+
0)
0&
#60
1"
#61
0"
0E
1D
0C
0@
1>
1=
1<
1:
15
11
10
1/
1.
0-
1,
1'
#62
1"
#63
0"
1E
1B
1A
1?
0>
0<
0;
0:
07
05
04
13
12
01
0/
1-
0,
1)
0(
0'
1&
#64
1"
#65
0"
0E
0B
1@
1>
18
17
03
02
1/
0-
1,
0+
0)
1'
0&
#66
1"
#67
0"
1E
0D
0?
0>
1<
1;
14
12
11
0.
0,
1+
0*
1(
1&
#68
1"
#69
0"
1C
1B
0A
0@
1?
1>
0;
1:
06
15
04
13
02
0/
1,
0+
0'
0&
#70
1"
#71
0"
0E
0B
1@
0>
0=
1;
0:
19
14
03
12
00
1/
1'
1&
#72
1"
#73
0"
1E
1D
0C
1B
0?
0<
0;
1:
09
16
05
13
02
1.
0,
1+
1*
1)
0(
0'
0&
#74
1"
#75
0"
0E
1?
1>
1<
1;
0:
19
08
07
06
03
12
0.
1,
1(
1&
#76
1"
#77
0"
#78
1"
#79
0"
1#
#80
1"
b10111110010110100001011011101010 F
